README.md
setup.cfg
setup.py
interfacer/__init__.py
interfacer/descdist.py
interfacer/fitdist.py
interfacer/jupyter_helper.py
interfacer/plotdist.py
interfacer/version.py
interfacer.egg-info/PKG-INFO
interfacer.egg-info/SOURCES.txt
interfacer.egg-info/dependency_links.txt
interfacer.egg-info/requires.txt
interfacer.egg-info/top_level.txt