Metadata-Version: 2.1
Name: interfacer
Version: 0.0.22.3
Summary: Pacote para facilitar a utilização do descdist em Python
Home-page: UNKNOWN
Author: Felipe Carlos
Author-email: felipe.carlos@inpe.br
License: UNKNOWN
Platform: UNKNOWN
